{"success":true,"ogLocale":"ja_JP","ogSiteName":"十勝岳ジオパーク 美瑛・上富良野エリア","ogType":"article","ogTitle":"白ひげの滝 | 十勝岳ジオパーク 美瑛・上富良野エリア","ogUrl":"https://tokachidake-geopark.jp/geoname/246/","articlePublishedTime":"2020-03-02T08:32:17+00:00","articleModifiedTime":"2023-03-03T07:06:44+00:00","articlePublisher":"https://www.facebook.com/tokachidakegeopark/","twitterCard":"summary","twitterSite":"@tokachidake_geo","twitterTitle":"白ひげの滝 | 十勝岳ジオパーク 美瑛・上富良野エリア","ogImage":[{"height":"630","url":"https://tokachidake-geopark.jp/wp/wp-content/uploads/2022/01/OGP_photo02-1.jpg","width":"1200","type":"jpg"}],"twitterImage":[{"url":"https://tokachidake-geopark.jp/wp/wp-content/uploads/2020/03/741c1a0bc0a2b01c06c4cc46ee34b596-scaled.jpg"}],"favicon":"https://i0.wp.com/tokachidake-geopark.jp/wp/wp-content/uploads/2020/03/cropped-app-icon-512x512-1.png?fit=32%2C32&ssl=1","charset":"UTF-8","jsonLD":[{"@context":"https://schema.org","@graph":[{"@type":"BreadcrumbList","@id":"https://tokachidake-geopark.jp/geoname/246/#breadcrumblist","itemListElement":[{"@type":"ListItem","@id":"https://tokachidake-geopark.jp#listItem","position":1,"name":"Home","item":"https://tokachidake-geopark.jp","nextItem":{"@type":"ListItem","@id":"https://tokachidake-geopark.jp/geoname/#listItem","name":"見どころ"}},{"@type":"ListItem","@id":"https://tokachidake-geopark.jp/geoname/#listItem","position":2,"name":"見どころ","item":"https://tokachidake-geopark.jp/geoname/","nextItem":{"@type":"ListItem","@id":"https://tokachidake-geopark.jp/geoname/genre_geoname/chishitsu-chikei/#listItem","name":"地質・地形サイト"},"previousItem":{"@type":"ListItem","@id":"https://tokachidake-geopark.jp#listItem","name":"Home"}},{"@type":"ListItem","@id":"https://tokachidake-geopark.jp/geoname/genre_geoname/chishitsu-chikei/#listItem","position":3,"name":"地質・地形サイト","item":"https://tokachidake-geopark.jp/geoname/genre_geoname/chishitsu-chikei/","nextItem":{"@type":"ListItem","@id":"https://tokachidake-geopark.jp/geoname/246/#listItem","name":"白ひげの滝"},"previousItem":{"@type":"ListItem","@id":"https://tokachidake-geopark.jp/geoname/#listItem","name":"見どころ"}},{"@type":"ListItem","@id":"https://tokachidake-geopark.jp/geoname/246/#listItem","position":4,"name":"白ひげの滝","previousItem":{"@type":"ListItem","@id":"https://tokachidake-geopark.jp/geoname/genre_geoname/chishitsu-chikei/#listItem","name":"地質・地形サイト"}}]},{"@type":"Organization","@id":"https://tokachidake-geopark.jp/#organization","name":"十勝岳ジオパーク 美瑛・上富良野エリア","url":"https://tokachidake-geopark.jp/","sameAs":["https://www.instagram.com/tokachidake_geo","https://www.youtube.com/channel/UCLi8WawyF_7zbyQpT8w0xMA"]},{"@type":"WebPage","@id":"https://tokachidake-geopark.jp/geoname/246/#webpage","url":"https://tokachidake-geopark.jp/geoname/246/","name":"白ひげの滝 | 十勝岳ジオパーク 美瑛・上富良野エリア","inLanguage":"ja","isPartOf":{"@id":"https://tokachidake-geopark.jp/#website"},"breadcrumb":{"@id":"https://tokachidake-geopark.jp/geoname/246/#breadcrumblist"},"datePublished":"2020-03-02T17:32:17+09:00","dateModified":"2023-03-03T16:06:44+09:00"},{"@type":"WebSite","@id":"https://tokachidake-geopark.jp/#website","url":"https://tokachidake-geopark.jp/","name":"十勝岳ジオパーク 美瑛・上富良野エリア","inLanguage":"ja","publisher":{"@id":"https://tokachidake-geopark.jp/#organization"}}]}],"requestUrl":"https://tokachidake-geopark.jp/geoname/246/"}