{"success":true,"author":"一般社團法人東北觀光推進機構","ogLocale":"zh_TW","ogSiteName":"東北觀光旅遊資訊網「旅東北」","ogUrl":"https://www.tohokukanko.jp/zh_TW/attractions/detail_1577.html","ogType":"article","twitterCard":"summary","twitterTitle":"鳥海山｜搜尋東北的觀光景點 | 旅東北 - 東北觀光旅遊資訊網","twitterDescription":"「鳥海山」是「日本百大名山」之一，從日本海海抜0公尺至標高2,236公尺處傲然矗立，十分罕見。山姿高雅，與富士山類似，又名「出羽富士」。從古至今，積雪的秀麗山姿都備受喜愛。從山頂遠眺景色美麗，由於是獨立山峰，視野遼闊，能欣賞醉人全景。整座山都獲…","ogImage":[{"url":"https://www.tohokukanko.jp/lsc/upfile/spot/0000/1577/1577_1_l.jpg","type":"jpg"}],"ogTitle":"鳥海山｜搜尋東北的觀光景點 | 旅東北 - 東北觀光旅遊資訊網","ogDescription":"「鳥海山」是「日本百大名山」之一，從日本海海抜0公尺至標高2,236公尺處傲然矗立，十分罕見。山姿高雅，與富士山類似，又名「出羽富士」。從古至今，積雪的秀麗山姿都備受喜愛。從山頂遠眺景色美麗，由於是獨立山峰，視野遼闊，能欣賞醉人全景。整座山都獲…","favicon":"https://www.tohokukanko.jp/favicon.ico","charset":"utf-8","requestUrl":"https://www.tohokukanko.jp/zh_TW/attractions/detail_1577.html"}